{
	"configurations" : 
	[
		{
			"directories" : 
			[
				{
					"build" : ".",
					"hasInstallRule" : true,
					"jsonFile" : "directory-.-b2f7598fa5b6cf449a2e.json",
					"minimumCMakeVersion" : 
					{
						"string" : "3.15"
					},
					"projectIndex" : 0,
					"source" : ".",
					"targetIndexes" : 
					[
						0,
						1,
						2,
						3,
						4
					]
				}
			],
			"name" : "",
			"projects" : 
			[
				{
					"directoryIndexes" : 
					[
						0
					],
					"name" : "robot_skills",
					"targetIndexes" : 
					[
						0,
						1,
						2,
						3,
						4
					]
				}
			],
			"targets" : 
			[
				{
					"directoryIndex" : 0,
					"id" : "MoveitHelper::@6890427a1f51a3e7e1df",
					"jsonFile" : "target-MoveitHelper-ab97bfc253ed2493e77b.json",
					"name" : "MoveitHelper",
					"projectIndex" : 0
				},
				{
					"directoryIndex" : 0,
					"id" : "SaveYaml::@6890427a1f51a3e7e1df",
					"jsonFile" : "target-SaveYaml-032a2651dce19f3e1096.json",
					"name" : "SaveYaml",
					"projectIndex" : 0
				},
				{
					"directoryIndex" : 0,
					"id" : "pick_place_server::@6890427a1f51a3e7e1df",
					"jsonFile" : "target-pick_place_server-e63c046adc3892d5d851.json",
					"name" : "pick_place_server",
					"projectIndex" : 0
				},
				{
					"directoryIndex" : 0,
					"id" : "robot_skills_uninstall::@6890427a1f51a3e7e1df",
					"jsonFile" : "target-robot_skills_uninstall-fb37f4cb1bf5d8f46093.json",
					"name" : "robot_skills_uninstall",
					"projectIndex" : 0
				},
				{
					"directoryIndex" : 0,
					"id" : "uninstall::@6890427a1f51a3e7e1df",
					"jsonFile" : "target-uninstall-cbe3c97a812867a00c3b.json",
					"name" : "uninstall",
					"projectIndex" : 0
				}
			]
		}
	],
	"kind" : "codemodel",
	"paths" : 
	{
		"build" : "/home/nicola/Desktop/Progetto_Sapore/build/robot_skills",
		"source" : "/home/nicola/Desktop/Progetto_Sapore/src/robot_skills"
	},
	"version" : 
	{
		"major" : 2,
		"minor" : 6
	}
}
